{
  "generated_at": "2026-06-20T21:04:10.890011",
  "version": "3.106",
  "script_hash": "5c3141dff1ad",
  "scan_hours": 72,
  "retention_days": 14,
  "activities": [
    {
      "activity_id": "i154917296",
      "date": "2026-06-07",
      "type": "Run",
      "name": "Badung Running",
      "interval_summary": [
        "8x 6m52s 147bpm",
        "1x 5m4s 151bpm"
      ],
      "intervals": [
        {
          "type": "WORK",
          "label": "412s@147bpm84rpm",
          "duration_secs": 417,
          "avg_hr": 135,
          "max_hr": 148,
          "avg_cadence": 83.057556,
          "zone": 1
        },
        {
          "type": "WORK",
          "label": "412s@147bpm84rpm",
          "duration_secs": 397,
          "avg_hr": 144,
          "max_hr": 153,
          "avg_cadence": 84.27456,
          "zone": 1
        },
        {
          "type": "WORK",
          "label": "412s@147bpm84rpm",
          "duration_secs": 394,
          "avg_hr": 144,
          "max_hr": 150,
          "avg_cadence": 86.63198,
          "zone": 1
        },
        {
          "type": "WORK",
          "label": "412s@147bpm84rpm",
          "duration_secs": 399,
          "avg_hr": 147,
          "max_hr": 154,
          "avg_cadence": 83.786964,
          "zone": 2
        },
        {
          "type": "WORK",
          "label": "412s@147bpm84rpm",
          "duration_secs": 418,
          "avg_hr": 152,
          "max_hr": 158,
          "avg_cadence": 84.56938,
          "zone": 2
        },
        {
          "type": "WORK",
          "label": "412s@147bpm84rpm",
          "duration_secs": 432,
          "avg_hr": 152,
          "max_hr": 159,
          "avg_cadence": 85.49537,
          "zone": 2
        },
        {
          "type": "WORK",
          "label": "412s@147bpm84rpm",
          "duration_secs": 419,
          "avg_hr": 153,
          "max_hr": 166,
          "avg_cadence": 84.03341,
          "zone": 2
        },
        {
          "type": "WORK",
          "label": "412s@147bpm84rpm",
          "duration_secs": 421,
          "avg_hr": 150,
          "max_hr": 160,
          "avg_cadence": 83.83135,
          "zone": 2
        },
        {
          "type": "WORK",
          "label": "304s@151bpm84rpm",
          "duration_secs": 304,
          "avg_hr": 151,
          "max_hr": 159,
          "avg_cadence": 83.539474,
          "zone": 2
        }
      ]
    },
    {
      "activity_id": "i155202284",
      "date": "2026-06-08",
      "type": "Swim",
      "name": "Lunch Swim",
      "interval_summary": [
        "1x 100m 102bpm",
        "1x 2m 125bpm",
        "6x 99m 124bpm",
        "1x 49m 114bpm",
        "4x 49m 141bpm",
        "1x 350m 134bpm",
        "1x 399m 138bpm",
        "1x 299m 136bpm"
      ],
      "intervals": [
        {
          "type": "RECOVERY",
          "duration_secs": 30,
          "avg_hr": 85,
          "max_hr": 93,
          "zone": 1
        },
        {
          "type": "WORK",
          "label": "126s@102bpm39rpm",
          "duration_secs": 126,
          "avg_hr": 102,
          "max_hr": 124,
          "avg_cadence": 39.02381,
          "zone": 1
        },
        {
          "type": "WORK",
          "label": "17s@125bpm3rpm",
          "duration_secs": 17,
          "avg_hr": 125,
          "max_hr": 126,
          "avg_cadence": 3.3333333,
          "zone": 1
        },
        {
          "type": "WORK",
          "label": "134s@124bpm33rpm",
          "duration_secs": 127,
          "avg_hr": 129,
          "max_hr": 137,
          "avg_cadence": 40.0,
          "zone": 1
        },
        {
          "type": "RECOVERY",
          "duration_secs": 60,
          "avg_hr": 116,
          "max_hr": 137,
          "zone": 1
        },
        {
          "type": "WORK",
          "label": "134s@124bpm33rpm",
          "duration_secs": 129,
          "avg_hr": 120,
          "max_hr": 131,
          "avg_cadence": 40.465115,
          "zone": 1
        },
        {
          "type": "RECOVERY",
          "duration_secs": 120,
          "avg_hr": 106,
          "max_hr": 131,
          "zone": 1
        },
        {
          "type": "WORK",
          "label": "134s@124bpm33rpm",
          "duration_secs": 135,
          "avg_hr": 119,
          "max_hr": 130,
          "zone": 1
        },
        {
          "type": "RECOVERY",
          "duration_secs": 33,
          "avg_hr": 121,
          "max_hr": 128,
          "zone": 1
        },
        {
          "type": "WORK",
          "label": "134s@124bpm33rpm",
          "duration_secs": 139,
          "avg_hr": 117,
          "max_hr": 124,
          "avg_cadence": 38.11702,
          "zone": 1
        },
        {
          "type": "RECOVERY",
          "duration_secs": 60,
          "avg_hr": 113,
          "max_hr": 124,
          "zone": 1
        },
        {
          "type": "WORK",
          "label": "66s@114bpm",
          "duration_secs": 66,
          "avg_hr": 114,
          "max_hr": 128,
          "zone": 1
        },
        {
          "type": "RECOVERY",
          "duration_secs": 1,
          "avg_hr": 128,
          "max_hr": 128,
          "zone": 1
        },
        {
          "type": "WORK",
          "label": "66s@141bpm35rpm",
          "duration_secs": 69,
          "avg_hr": 129,
          "max_hr": 137,
          "zone": 1
        },
        {
          "type": "RECOVERY",
          "duration_secs": 42,
          "avg_hr": 125,
          "max_hr": 139,
          "zone": 1
        },
        {
          "type": "WORK",
          "label": "134s@124bpm33rpm",
          "duration_secs": 131,
          "avg_hr": 129,
          "max_hr": 143,
          "avg_cadence": 40.45977,
          "zone": 1
        },
        {
          "type": "RECOVERY",
          "duration_secs": 18,
          "avg_hr": 137,
          "max_hr": 143,
          "zone": 1
        },
        {
          "type": "WORK",
          "label": "134s@124bpm33rpm",
          "duration_secs": 142,
          "avg_hr": 131,
          "max_hr": 139,
          "avg_cadence": 39.65263,
          "zone": 1
        },
        {
          "type": "RECOVERY",
          "duration_secs": 155,
          "avg_hr": 107,
          "max_hr": 138,
          "zone": 1
        },
        {
          "type": "WORK",
          "label": "493s@134bpm41rpm",
          "duration_secs": 493,
          "avg_hr": 134,
          "max_hr": 147,
          "avg_cadence": 41.236362,
          "zone": 1
        },
        {
          "type": "RECOVERY",
          "duration_secs": 3,
          "avg_hr": 143,
          "max_hr": 143,
          "zone": 1
        },
        {
          "type": "WORK",
          "label": "66s@141bpm35rpm",
          "duration_secs": 70,
          "avg_hr": 143,
          "max_hr": 147,
          "avg_cadence": 42.085106,
          "zone": 1
        },
        {
          "type": "RECOVERY",
          "duration_secs": 15,
          "avg_hr": 143,
          "max_hr": 147,
          "zone": 1
        },
        {
          "type": "WORK",
          "label": "66s@141bpm35rpm",
          "duration_secs": 60,
          "avg_hr": 142,
          "max_hr": 156,
          "avg_cadence": 46.8,
          "zone": 1
        },
        {
          "type": "RECOVERY",
          "duration_secs": 27,
          "avg_hr": 153,
          "max_hr": 160,
          "zone": 2
        },
        {
          "type": "WORK",
          "label": "604s@138bpm43rpm",
          "duration_secs": 604,
          "avg_hr": 138,
          "max_hr": 147,
          "avg_cadence": 42.6,
          "zone": 1
        },
        {
          "type": "RECOVERY",
          "duration_secs": 16,
          "avg_hr": 141,
          "max_hr": 144,
          "zone": 1
        },
        {
          "type": "WORK",
          "label": "66s@141bpm35rpm",
          "duration_secs": 66,
          "avg_hr": 149,
          "max_hr": 162,
          "avg_cadence": 51.0,
          "zone": 2
        },
        {
          "type": "RECOVERY",
          "duration_secs": 173,
          "avg_hr": 124,
          "max_hr": 162,
          "zone": 1
        },
        {
          "type": "WORK",
          "label": "438s@136bpm43rpm",
          "duration_secs": 438,
          "avg_hr": 136,
          "max_hr": 149,
          "avg_cadence": 42.866894,
          "zone": 1
        },
        {
          "type": "RECOVERY",
          "duration_secs": 20,
          "avg_hr": 145,
          "max_hr": 150,
          "zone": 1
        }
      ]
    },
    {
      "activity_id": "i155911392",
      "date": "2026-06-10",
      "type": "Run",
      "name": "Badung - No Let Up",
      "interval_summary": [
        "1x 5m1s 125bpm",
        "2x 3m3s 147bpm",
        "1x 2m 145bpm"
      ],
      "intervals": [
        {
          "type": "WORK",
          "label": "301s@125bpm83rpm",
          "duration_secs": 301,
          "avg_hr": 125,
          "max_hr": 139,
          "avg_cadence": 83.45847,
          "zone": 1
        },
        {
          "type": "WORK",
          "label": "183s@147bpm87rpm",
          "duration_secs": 180,
          "avg_hr": 140,
          "max_hr": 153,
          "avg_cadence": 85.727776,
          "zone": 1
        },
        {
          "type": "WORK",
          "label": "120s@145bpm85rpm",
          "duration_secs": 120,
          "avg_hr": 145,
          "max_hr": 154,
          "avg_cadence": 85.416664,
          "zone": 1
        },
        {
          "type": "RECOVERY",
          "duration_secs": 180,
          "avg_hr": 137,
          "max_hr": 146,
          "avg_cadence": 81.57222,
          "zone": 1
        },
        {
          "type": "WORK",
          "label": "183s@147bpm87rpm",
          "duration_secs": 186,
          "avg_hr": 153,
          "max_hr": 160,
          "avg_cadence": 87.89247,
          "zone": 2
        }
      ]
    },
    {
      "activity_id": "i156589058",
      "date": "2026-06-12",
      "type": "Swim",
      "name": "Afternoon Swim",
      "interval_summary": [
        "1x 150m 103bpm",
        "1x 50m 118bpm",
        "4x 74m 110bpm",
        "4x 25m 120bpm",
        "10x 99m 123bpm",
        "4x 49m 116bpm",
        "1x 125m 126bpm",
        "1x 23m 88bpm",
        "1x 23m 100bpm",
        "1x 23m 115bpm",
        "1x 199m 120bpm"
      ],
      "intervals": [
        {
          "type": "RECOVERY",
          "duration_secs": 46,
          "avg_hr": 84,
          "max_hr": 88,
          "zone": 1
        },
        {
          "type": "WORK",
          "label": "178s@103bpm39rpm",
          "duration_secs": 178,
          "avg_hr": 103,
          "max_hr": 131,
          "avg_cadence": 39.18182,
          "zone": 1
        },
        {
          "type": "RECOVERY",
          "duration_secs": 15,
          "avg_hr": 128,
          "max_hr": 131,
          "zone": 1
        },
        {
          "type": "WORK",
          "label": "55s@118bpm45rpm",
          "duration_secs": 55,
          "avg_hr": 118,
          "max_hr": 134,
          "avg_cadence": 45.2973,
          "zone": 1
        },
        {
          "type": "RECOVERY",
          "duration_secs": 63,
          "avg_hr": 120,
          "max_hr": 137,
          "zone": 1
        },
        {
          "type": "WORK",
          "label": "98s@110bpm31rpm",
          "duration_secs": 93,
          "avg_hr": 102,
          "max_hr": 122,
          "avg_cadence": 40.650795,
          "zone": 1
        },
        {
          "type": "RECOVERY",
          "duration_secs": 1,
          "avg_hr": 123,
          "max_hr": 123,
          "zone": 1
        },
        {
          "type": "WORK",
          "label": "31s@120bpm28rpm",
          "duration_secs": 31,
          "avg_hr": 125,
          "max_hr": 130,
          "avg_cadence": 36.190475,
          "zone": 1
        },
        {
          "type": "RECOVERY",
          "duration_secs": 21,
          "avg_hr": 130,
          "max_hr": 131,
          "zone": 1
        },
        {
          "type": "WORK",
          "label": "130s@123bpm43rpm",
          "duration_secs": 124,
          "avg_hr": 131,
          "max_hr": 144,
          "avg_cadence": 42.93976,
          "zone": 1
        },
        {
          "type": "RECOVERY",
          "duration_secs": 72,
          "avg_hr": 121,
          "max_hr": 144,
          "zone": 1
        },
        {
          "type": "WORK",
          "label": "66s@116bpm38rpm",
          "duration_secs": 62,
          "avg_hr": 105,
          "max_hr": 118,
          "avg_cadence": 38.190475,
          "zone": 1
        },
        {
          "type": "RECOVERY",
          "duration_secs": 16,
          "avg_hr": 120,
          "max_hr": 121,
          "zone": 1
        },
        {
          "type": "WORK",
          "label": "31s@120bpm28rpm",
          "duration_secs": 28,
          "avg_hr": 116,
          "max_hr": 120,
          "avg_cadence": 37.894737,
          "zone": 1
        },
        {
          "type": "RECOVERY",
          "duration_secs": 2,
          "avg_hr": 116,
          "max_hr": 116,
          "zone": 1
        },
        {
          "type": "WORK",
          "label": "166s@126bpm41rpm",
          "duration_secs": 166,
          "avg_hr": 126,
          "max_hr": 132,
          "avg_cadence": 41.243244,
          "zone": 1
        },
        {
          "type": "RECOVERY",
          "duration_secs": 84,
          "avg_hr": 114,
          "max_hr": 132,
          "zone": 1
        },
        {
          "type": "WORK",
          "label": "130s@123bpm43rpm",
          "duration_secs": 118,
          "avg_hr": 116,
          "max_hr": 130,
          "avg_cadence": 43.814816,
          "zone": 1
        },
        {
          "type": "RECOVERY",
          "duration_secs": 69,
          "avg_hr": 118,
          "max_hr": 131,
          "zone": 1
        },
        {
          "type": "WORK",
          "label": "130s@123bpm43rpm",
          "duration_secs": 130,
          "avg_hr": 110,
          "max_hr": 122,
          "avg_cadence": 40.764046,
          "zone": 1
        },
        {
          "type": "RECOVERY",
          "duration_secs": 16,
          "avg_hr": 123,
          "max_hr": 124,
          "zone": 1
        },
        {
          "type": "WORK",
          "label": "130s@123bpm43rpm",
          "duration_secs": 128,
          "avg_hr": 124,
          "max_hr": 131,
          "avg_cadence": 43.44706,
          "zone": 1
        },
        {
          "type": "RECOVERY",
          "duration_secs": 20,
          "avg_hr": 130,
          "max_hr": 132,
          "zone": 1
        },
        {
          "type": "WORK",
          "label": "130s@123bpm43rpm",
          "duration_secs": 129,
          "avg_hr": 128,
          "max_hr": 138,
          "avg_cadence": 44.95402,
          "zone": 1
        },
        {
          "type": "RECOVERY",
          "duration_secs": 15,
          "avg_hr": 135,
          "max_hr": 138,
          "zone": 1
        },
        {
          "type": "WORK",
          "label": "130s@123bpm43rpm",
          "duration_secs": 136,
          "avg_hr": 125,
          "max_hr": 131,
          "avg_cadence": 44.42857,
          "zone": 1
        },
        {
          "type": "RECOVERY",
          "duration_secs": 65,
          "avg_hr": 126,
          "max_hr": 127,
          "zone": 1
        },
        {
          "type": "WORK",
          "label": "130s@123bpm43rpm",
          "duration_secs": 136,
          "avg_hr": 115,
          "max_hr": 127,
          "avg_cadence": 39.79348,
          "zone": 1
        },
        {
          "type": "RECOVERY",
          "duration_secs": 35,
          "avg_hr": 122,
          "max_hr": 123,
          "zone": 1
        },
        {
          "type": "WORK",
          "label": "66s@116bpm38rpm",
          "duration_secs": 69,
          "avg_hr": 118,
          "max_hr": 124,
          "avg_cadence": 36.347828,
          "zone": 1
        },
        {
          "type": "RECOVERY",
          "duration_secs": 1,
          "avg_hr": 124,
          "max_hr": 124,
          "zone": 1
        },
        {
          "type": "WORK",
          "label": "66s@116bpm38rpm",
          "duration_secs": 66,
          "avg_hr": 128,
          "max_hr": 135,
          "avg_cadence": 41.045456,
          "zone": 1
        },
        {
          "type": "RECOVERY",
          "duration_secs": 38,
          "avg_hr": 135,
          "max_hr": 137,
          "zone": 1
        },
        {
          "type": "WORK",
          "label": "31s@120bpm28rpm",
          "duration_secs": 32,
          "avg_hr": 119,
          "max_hr": 135,
          "avg_cadence": 38.18182,
          "zone": 1
        },
        {
          "type": "RECOVERY",
          "duration_secs": 2,
          "avg_hr": 116,
          "max_hr": 116,
          "zone": 1
        },
        {
          "type": "WORK",
          "label": "98s@110bpm31rpm",
          "duration_secs": 100,
          "avg_hr": 122,
          "max_hr": 129,
          "avg_cadence": 41.373135,
          "zone": 1
        },
        {
          "type": "RECOVERY",
          "duration_secs": 27,
          "avg_hr": 126,
          "max_hr": 130,
          "zone": 1
        },
        {
          "type": "WORK",
          "label": "130s@123bpm43rpm",
          "duration_secs": 128,
          "avg_hr": 124,
          "max_hr": 135,
          "avg_cadence": 41.895348,
          "zone": 1
        },
        {
          "type": "RECOVERY",
          "duration_secs": 15,
          "avg_hr": 135,
          "max_hr": 137,
          "zone": 1
        },
        {
          "type": "WORK",
          "label": "130s@123bpm43rpm",
          "duration_secs": 139,
          "avg_hr": 132,
          "max_hr": 150,
          "avg_cadence": 46.83871,
          "zone": 1
        },
        {
          "type": "RECOVERY",
          "duration_secs": 150,
          "avg_hr": 120,
          "max_hr": 146,
          "zone": 1
        },
        {
          "type": "WORK",
          "label": "130s@123bpm43rpm",
          "duration_secs": 131,
          "avg_hr": 122,
          "max_hr": 133,
          "avg_cadence": 41.517242,
          "zone": 1
        },
        {
          "type": "RECOVERY",
          "duration_secs": 85,
          "avg_hr": 114,
          "max_hr": 135,
          "zone": 1
        },
        {
          "type": "WORK",
          "label": "98s@110bpm31rpm",
          "duration_secs": 99,
          "avg_hr": 105,
          "max_hr": 116,
          "zone": 1
        },
        {
          "type": "WORK",
          "label": "31s@120bpm28rpm",
          "duration_secs": 34,
          "avg_hr": 119,
          "max_hr": 122,
          "zone": 1
        },
        {
          "type": "RECOVERY",
          "duration_secs": 232,
          "avg_hr": 96,
          "max_hr": 124,
          "zone": 1
        },
        {
          "type": "WORK",
          "label": "32s@88bpm40rpm",
          "duration_secs": 32,
          "avg_hr": 88,
          "max_hr": 99,
          "avg_cadence": 40.0,
          "zone": 1
        },
        {
          "type": "RECOVERY",
          "duration_secs": 3,
          "avg_hr": 99,
          "max_hr": 99,
          "zone": 1
        },
        {
          "type": "WORK",
          "label": "98s@110bpm31rpm",
          "duration_secs": 99,
          "avg_hr": 112,
          "max_hr": 125,
          "avg_cadence": 41.666668,
          "zone": 1
        },
        {
          "type": "RECOVERY",
          "duration_secs": 24,
          "avg_hr": 122,
          "max_hr": 125,
          "zone": 1
        },
        {
          "type": "WORK",
          "label": "66s@116bpm38rpm",
          "duration_secs": 66,
          "avg_hr": 113,
          "max_hr": 125,
          "avg_cadence": 36.0,
          "zone": 1
        },
        {
          "type": "RECOVERY",
          "duration_secs": 87,
          "avg_hr": 110,
          "max_hr": 125,
          "zone": 1
        },
        {
          "type": "WORK",
          "label": "42s@100bpm",
          "duration_secs": 42,
          "avg_hr": 100,
          "max_hr": 113,
          "zone": 1
        },
        {
          "type": "RECOVERY",
          "duration_secs": 3,
          "avg_hr": 108,
          "max_hr": 109,
          "zone": 1
        },
        {
          "type": "WORK",
          "label": "24s@115bpm53rpm",
          "duration_secs": 24,
          "avg_hr": 115,
          "max_hr": 126,
          "avg_cadence": 52.5,
          "zone": 1
        },
        {
          "type": "RECOVERY",
          "duration_secs": 36,
          "avg_hr": 126,
          "max_hr": 133,
          "zone": 1
        },
        {
          "type": "WORK",
          "label": "279s@120bpm43rpm",
          "duration_secs": 279,
          "avg_hr": 120,
          "max_hr": 132,
          "avg_cadence": 42.99465,
          "zone": 1
        },
        {
          "type": "RECOVERY",
          "duration_secs": 3,
          "avg_hr": 129,
          "max_hr": 129,
          "zone": 1
        }
      ]
    },
    {
      "activity_id": "i156816318",
      "date": "2026-06-13",
      "type": "Run",
      "name": "Badung Running",
      "interval_summary": [
        "2x 7m16s 149bpm",
        "1x 5m31s 152bpm"
      ],
      "intervals": [
        {
          "type": "WORK",
          "label": "436s@149bpm85rpm",
          "duration_secs": 422,
          "avg_hr": 145,
          "max_hr": 157,
          "avg_cadence": 85.21564,
          "zone": 1
        },
        {
          "type": "WORK",
          "label": "436s@149bpm85rpm",
          "duration_secs": 450,
          "avg_hr": 152,
          "max_hr": 158,
          "avg_cadence": 84.064445,
          "zone": 2
        },
        {
          "type": "WORK",
          "label": "331s@152bpm83rpm",
          "duration_secs": 331,
          "avg_hr": 152,
          "max_hr": 158,
          "avg_cadence": 82.912384,
          "zone": 2
        }
      ]
    },
    {
      "activity_id": "i157389295",
      "date": "2026-06-15",
      "type": "Swim",
      "name": "Afternoon Swim",
      "interval_summary": [
        "1x 175m 101bpm",
        "2x 199m 122bpm",
        "1x 25m 117bpm",
        "1x 451m 123bpm",
        "1x 849m 134bpm"
      ],
      "intervals": [
        {
          "type": "RECOVERY",
          "duration_secs": 15,
          "avg_hr": 88,
          "max_hr": 96,
          "zone": 1
        },
        {
          "type": "WORK",
          "label": "226s@101bpm39rpm",
          "duration_secs": 226,
          "avg_hr": 101,
          "max_hr": 120,
          "avg_cadence": 38.86842,
          "zone": 1
        },
        {
          "type": "RECOVERY",
          "duration_secs": 8,
          "avg_hr": 116,
          "max_hr": 118,
          "zone": 1
        },
        {
          "type": "WORK",
          "label": "276s@122bpm38rpm",
          "duration_secs": 274,
          "avg_hr": 118,
          "max_hr": 124,
          "avg_cadence": 37.408604,
          "zone": 1
        },
        {
          "type": "RECOVERY",
          "duration_secs": 5,
          "avg_hr": 121,
          "max_hr": 122,
          "zone": 1
        },
        {
          "type": "WORK",
          "label": "31s@117bpm38rpm",
          "duration_secs": 31,
          "avg_hr": 117,
          "max_hr": 123,
          "avg_cadence": 38.095238,
          "zone": 1
        },
        {
          "type": "RECOVERY",
          "duration_secs": 2,
          "avg_hr": 124,
          "max_hr": 124,
          "zone": 1
        },
        {
          "type": "WORK",
          "label": "635s@123bpm39rpm",
          "duration_secs": 635,
          "avg_hr": 123,
          "max_hr": 131,
          "avg_cadence": 39.219112,
          "zone": 1
        },
        {
          "type": "RECOVERY",
          "duration_secs": 2,
          "avg_hr": 130,
          "max_hr": 130,
          "zone": 1
        },
        {
          "type": "WORK",
          "label": "276s@122bpm38rpm",
          "duration_secs": 277,
          "avg_hr": 126,
          "max_hr": 131,
          "avg_cadence": 38.967915,
          "zone": 1
        },
        {
          "type": "WORK",
          "label": "1194s@134bpm41rpm",
          "duration_secs": 1194,
          "avg_hr": 134,
          "max_hr": 158,
          "avg_cadence": 41.01363,
          "zone": 1
        },
        {
          "type": "RECOVERY",
          "duration_secs": 50,
          "avg_hr": 140,
          "max_hr": 159,
          "zone": 1
        }
      ]
    },
    {
      "activity_id": "i157666134",
      "date": "2026-06-16",
      "type": "Run",
      "name": "Badung Running",
      "interval_summary": [
        "10x 6m56s 147bpm",
        "1x 43s 160bpm"
      ],
      "intervals": [
        {
          "type": "WORK",
          "label": "416s@147bpm88rpm",
          "duration_secs": 428,
          "avg_hr": 130,
          "max_hr": 143,
          "avg_cadence": 86.01869,
          "zone": 1
        },
        {
          "type": "RECOVERY",
          "duration_secs": 1,
          "avg_hr": 140,
          "max_hr": 140,
          "avg_cadence": 87.0,
          "zone": 1
        },
        {
          "type": "WORK",
          "label": "416s@147bpm88rpm",
          "duration_secs": 422,
          "avg_hr": 141,
          "max_hr": 149,
          "avg_cadence": 85.98104,
          "zone": 1
        },
        {
          "type": "WORK",
          "label": "416s@147bpm88rpm",
          "duration_secs": 403,
          "avg_hr": 142,
          "max_hr": 151,
          "avg_cadence": 89.15633,
          "zone": 1
        },
        {
          "type": "WORK",
          "label": "416s@147bpm88rpm",
          "duration_secs": 396,
          "avg_hr": 146,
          "max_hr": 152,
          "avg_cadence": 87.628784,
          "zone": 1
        },
        {
          "type": "WORK",
          "label": "416s@147bpm88rpm",
          "duration_secs": 416,
          "avg_hr": 148,
          "max_hr": 155,
          "avg_cadence": 88.21635,
          "zone": 2
        },
        {
          "type": "WORK",
          "label": "416s@147bpm88rpm",
          "duration_secs": 420,
          "avg_hr": 153,
          "max_hr": 158,
          "avg_cadence": 88.833336,
          "zone": 2
        },
        {
          "type": "WORK",
          "label": "416s@147bpm88rpm",
          "duration_secs": 430,
          "avg_hr": 152,
          "max_hr": 162,
          "avg_cadence": 86.12558,
          "zone": 2
        },
        {
          "type": "WORK",
          "label": "416s@147bpm88rpm",
          "duration_secs": 400,
          "avg_hr": 152,
          "max_hr": 162,
          "avg_cadence": 89.1875,
          "zone": 2
        },
        {
          "type": "WORK",
          "label": "416s@147bpm88rpm",
          "duration_secs": 424,
          "avg_hr": 152,
          "max_hr": 158,
          "avg_cadence": 88.330185,
          "zone": 2
        },
        {
          "type": "WORK",
          "label": "416s@147bpm88rpm",
          "duration_secs": 418,
          "avg_hr": 154,
          "max_hr": 162,
          "avg_cadence": 89.48086,
          "zone": 2
        },
        {
          "type": "WORK",
          "label": "43s@160bpm89rpm",
          "duration_secs": 43,
          "avg_hr": 160,
          "max_hr": 161,
          "avg_cadence": 89.23256,
          "zone": 3
        }
      ]
    },
    {
      "activity_id": "i158579073",
      "date": "2026-06-19",
      "type": "Ride",
      "name": "Bad Lausick Road Cycling",
      "interval_summary": [
        "10x 30s 197w",
        "1x 25s 265w",
        "1x 12s 290w",
        "2x 2m9s 162w",
        "1x 60s 187w",
        "2x 3m24s 151w",
        "3x 92s 161w",
        "1x 1m52s 164w",
        "1x 2m51s 151w",
        "1x 3m53s 136w",
        "1x 17s 281w"
      ],
      "intervals": [
        {
          "type": "RECOVERY",
          "duration_secs": 104,
          "avg_power": 85,
          "max_power": 273,
          "avg_hr": 92,
          "max_hr": 118,
          "avg_cadence": 49.936844,
          "zone": 1,
          "training_load": 1.2885753,
          "decoupling": -173.58691
        },
        {
          "type": "WORK",
          "label": "30s@197w84rpm",
          "duration_secs": 31,
          "avg_power": 200,
          "max_power": 248,
          "avg_hr": 113,
          "max_hr": 122,
          "avg_cadence": 85.3871,
          "zone": 5,
          "training_load": 1.2203956,
          "decoupling": -15.4298725
        },
        {
          "type": "RECOVERY",
          "duration_secs": 94,
          "avg_power": 116,
          "max_power": 245,
          "avg_hr": 121,
          "max_hr": 130,
          "avg_cadence": 69.03191,
          "zone": 2,
          "training_load": 1.9720254,
          "decoupling": 4.354769
        },
        {
          "type": "WORK",
          "label": "30s@197w84rpm",
          "duration_secs": 35,
          "avg_power": 238,
          "max_power": 302,
          "avg_hr": 127,
          "max_hr": 134,
          "avg_cadence": 69.28571,
          "zone": 6,
          "training_load": 1.296434,
          "decoupling": -13.900252
        },
        {
          "type": "WORK",
          "label": "25s@265w58rpm",
          "duration_secs": 25,
          "avg_power": 265,
          "max_power": 350,
          "avg_hr": 138,
          "max_hr": 142,
          "avg_cadence": 57.64,
          "zone": 7,
          "training_load": 1.7148526,
          "decoupling": 23.28726
        },
        {
          "type": "RECOVERY",
          "duration_secs": 197,
          "avg_power": 93,
          "max_power": 243,
          "avg_hr": 118,
          "max_hr": 141,
          "avg_cadence": 62.187817,
          "zone": 2,
          "training_load": 3.9095056,
          "decoupling": 6.5150905
        },
        {
          "type": "WORK",
          "label": "12s@290w86rpm",
          "duration_secs": 12,
          "avg_power": 290,
          "max_power": 318,
          "avg_hr": 116,
          "max_hr": 121,
          "avg_cadence": 85.916664,
          "zone": 7,
          "training_load": 0.2728647,
          "decoupling": -1.7850277
        },
        {
          "type": "RECOVERY",
          "duration_secs": 2590,
          "avg_power": 118,
          "max_power": 290,
          "avg_hr": 114,
          "max_hr": 138,
          "avg_cadence": 62.85685,
          "zone": 2,
          "training_load": 9.882913
        },
        {
          "type": "WORK",
          "label": "129s@162w85rpm",
          "duration_secs": 128,
          "avg_power": 163,
          "max_power": 232,
          "avg_hr": 133,
          "max_hr": 142,
          "avg_cadence": 84.34375,
          "zone": 4,
          "training_load": 3.3061225,
          "decoupling": 4.2527885
        },
        {
          "type": "RECOVERY",
          "duration_secs": 347,
          "avg_power": 89,
          "max_power": 313,
          "avg_hr": 117,
          "max_hr": 140,
          "avg_cadence": 49.32565,
          "zone": 1,
          "training_load": 5.421875,
          "decoupling": 1.4476202
        },
        {
          "type": "WORK",
          "label": "60s@187w80rpm",
          "duration_secs": 60,
          "avg_power": 187,
          "max_power": 253,
          "avg_hr": 126,
          "max_hr": 133,
          "avg_cadence": 80.333336,
          "zone": 5,
          "training_load": 1.7878401,
          "decoupling": 9.048455
        },
        {
          "type": "RECOVERY",
          "duration_secs": 271,
          "avg_power": 141,
          "max_power": 292,
          "avg_hr": 128,
          "max_hr": 136,
          "avg_cadence": 74.80812,
          "zone": 3,
          "training_load": 6.001098,
          "decoupling": -6.047228
        },
        {
          "type": "WORK",
          "label": "30s@197w84rpm",
          "duration_secs": 25,
          "avg_power": 178,
          "max_power": 226,
          "avg_hr": 127,
          "max_hr": 131,
          "avg_cadence": 85.8,
          "zone": 5,
          "training_load": 0.71946746,
          "decoupling": 16.733467
        },
        {
          "type": "RECOVERY",
          "duration_secs": 283,
          "avg_power": 113,
          "max_power": 231,
          "avg_hr": 124,
          "max_hr": 133,
          "avg_cadence": 69.76325,
          "zone": 2,
          "training_load": 4.926842,
          "decoupling": 11.754159
        },
        {
          "type": "WORK",
          "label": "30s@197w84rpm",
          "duration_secs": 36,
          "avg_power": 221,
          "max_power": 275,
          "avg_hr": 123,
          "max_hr": 131,
          "avg_cadence": 81.80556,
          "zone": 6,
          "training_load": 1.2126205,
          "decoupling": 22.119192
        },
        {
          "type": "RECOVERY",
          "duration_secs": 259,
          "avg_power": 139,
          "max_power": 272,
          "avg_hr": 130,
          "max_hr": 139,
          "avg_cadence": 72.671814,
          "zone": 3,
          "training_load": 6.2831583,
          "decoupling": -9.280421
        },
        {
          "type": "WORK",
          "label": "204s@151w88rpm",
          "duration_secs": 204,
          "avg_power": 149,
          "max_power": 203,
          "avg_hr": 132,
          "max_hr": 137,
          "avg_cadence": 85.84314,
          "zone": 3,
          "training_load": 4.7615743,
          "decoupling": -0.5149939
        },
        {
          "type": "RECOVERY",
          "duration_secs": 429,
          "avg_power": 130,
          "max_power": 286,
          "avg_hr": 129,
          "max_hr": 141,
          "avg_cadence": 75.48252,
          "zone": 3,
          "training_load": 8.513594,
          "decoupling": 5.02858
        },
        {
          "type": "WORK",
          "label": "92s@161w90rpm",
          "duration_secs": 90,
          "avg_power": 162,
          "max_power": 238,
          "avg_hr": 133,
          "max_hr": 140,
          "avg_cadence": 87.01111,
          "zone": 4,
          "training_load": 2.2393177,
          "decoupling": 12.77676
        },
        {
          "type": "RECOVERY",
          "duration_secs": 938,
          "avg_power": 136,
          "max_power": 289,
          "avg_hr": 134,
          "max_hr": 145,
          "avg_cadence": 81.1258,
          "zone": 3,
          "training_load": 18.877907,
          "decoupling": -9.079453
        },
        {
          "type": "WORK",
          "label": "92s@161w90rpm",
          "duration_secs": 100,
          "avg_power": 161,
          "max_power": 219,
          "avg_hr": 144,
          "max_hr": 149,
          "avg_cadence": 94.04,
          "zone": 4,
          "training_load": 2.4259298,
          "decoupling": -3.5134873
        },
        {
          "type": "RECOVERY",
          "duration_secs": 773,
          "avg_power": 134,
          "max_power": 303,
          "avg_hr": 138,
          "max_hr": 149,
          "avg_cadence": 81.09702,
          "zone": 3,
          "training_load": 14.911265,
          "decoupling": 0.101381786
        },
        {
          "type": "WORK",
          "label": "30s@197w84rpm",
          "duration_secs": 32,
          "avg_power": 215,
          "max_power": 281,
          "avg_hr": 145,
          "max_hr": 148,
          "avg_cadence": 83.5625,
          "zone": 6,
          "training_load": 1.1975623,
          "decoupling": 14.021837
        },
        {
          "type": "RECOVERY",
          "duration_secs": 42,
          "avg_power": 108,
          "max_power": 175,
          "avg_hr": 142,
          "max_hr": 147,
          "avg_cadence": 79.54762,
          "zone": 2,
          "training_load": 1.0059524,
          "decoupling": -10.842743
        },
        {
          "type": "WORK",
          "label": "92s@161w90rpm",
          "duration_secs": 85,
          "avg_power": 159,
          "max_power": 202,
          "avg_hr": 140,
          "max_hr": 146,
          "avg_cadence": 89.858826,
          "zone": 4,
          "training_load": 1.9583068,
          "decoupling": 1.1417382
        },
        {
          "type": "RECOVERY",
          "duration_secs": 700,
          "avg_power": 115,
          "max_power": 285,
          "avg_hr": 135,
          "max_hr": 149,
          "avg_cadence": 70.55857,
          "zone": 2,
          "training_load": 11.464534,
          "decoupling": 4.8382845
        },
        {
          "type": "WORK",
          "label": "30s@197w84rpm",
          "duration_secs": 28,
          "avg_power": 181,
          "max_power": 254,
          "avg_hr": 147,
          "max_hr": 149,
          "avg_cadence": 92.03571,
          "zone": 5,
          "training_load": 0.6620646,
          "decoupling": -1.3696997
        },
        {
          "type": "RECOVERY",
          "duration_secs": 95,
          "avg_power": 137,
          "max_power": 278,
          "avg_hr": 148,
          "max_hr": 151,
          "avg_cadence": 81.063156,
          "zone": 3,
          "training_load": 2.0203993,
          "decoupling": 10.7373085
        },
        {
          "type": "WORK",
          "label": "112s@164w93rpm",
          "duration_secs": 112,
          "avg_power": 164,
          "max_power": 218,
          "avg_hr": 146,
          "max_hr": 150,
          "avg_cadence": 92.55357,
          "zone": 4,
          "training_load": 3.000992,
          "decoupling": -1.4068334
        },
        {
          "type": "RECOVERY",
          "duration_secs": 446,
          "avg_power": 136,
          "max_power": 405,
          "avg_hr": 145,
          "max_hr": 151,
          "avg_cadence": 80.28075,
          "zone": 3,
          "training_load": 7.632653,
          "decoupling": -2.9961832
        },
        {
          "type": "WORK",
          "label": "30s@197w84rpm",
          "duration_secs": 27,
          "avg_power": 179,
          "max_power": 248,
          "avg_hr": 143,
          "max_hr": 149,
          "avg_cadence": 92.44444,
          "zone": 5,
          "training_load": 0.88990754,
          "decoupling": 21.500162
        },
        {
          "type": "RECOVERY",
          "duration_secs": 141,
          "avg_power": 115,
          "max_power": 381,
          "avg_hr": 147,
          "max_hr": 153,
          "avg_cadence": 63.770992,
          "zone": 2,
          "training_load": 2.3856027,
          "decoupling": -43.83
        },
        {
          "type": "WORK",
          "label": "171s@151w91rpm",
          "duration_secs": 171,
          "avg_power": 151,
          "max_power": 215,
          "avg_hr": 152,
          "max_hr": 156,
          "avg_cadence": 91.42105,
          "zone": 3,
          "training_load": 3.9396524,
          "decoupling": -2.1535385
        },
        {
          "type": "RECOVERY",
          "duration_secs": 440,
          "avg_power": 113,
          "max_power": 322,
          "avg_hr": 140,
          "max_hr": 152,
          "avg_cadence": 70.818184,
          "zone": 2,
          "training_load": 7.0261216,
          "decoupling": -13.877935
        },
        {
          "type": "WORK",
          "label": "30s@197w84rpm",
          "duration_secs": 26,
          "avg_power": 177,
          "max_power": 211,
          "avg_hr": 147,
          "max_hr": 149,
          "avg_cadence": 95.46154,
          "zone": 5,
          "training_load": 0.5757511,
          "decoupling": 2.5497577
        },
        {
          "type": "RECOVERY",
          "duration_secs": 50,
          "avg_power": 64,
          "max_power": 201,
          "avg_hr": 140,
          "max_hr": 148,
          "avg_cadence": 38.92,
          "zone": 1,
          "training_load": 0.6736288,
          "decoupling": -30.379295
        },
        {
          "type": "WORK",
          "label": "30s@197w84rpm",
          "duration_secs": 31,
          "avg_power": 196,
          "max_power": 245,
          "avg_hr": 142,
          "max_hr": 152,
          "avg_cadence": 78.77419,
          "zone": 5,
          "training_load": 0.7616489,
          "decoupling": 21.203608
        },
        {
          "type": "RECOVERY",
          "duration_secs": 3,
          "avg_power": 146,
          "max_power": 170,
          "avg_hr": 153,
          "max_hr": 153,
          "avg_cadence": 81.0,
          "zone": 3,
          "training_load": 0.1077127,
          "decoupling": 20.882353
        },
        {
          "type": "WORK",
          "label": "233s@136w89rpm",
          "duration_secs": 233,
          "avg_power": 136,
          "max_power": 214,
          "avg_hr": 146,
          "max_hr": 153,
          "avg_cadence": 88.55794,
          "zone": 3,
          "training_load": 4.5590367,
          "decoupling": 2.8401852
        },
        {
          "type": "RECOVERY",
          "duration_secs": 397,
          "avg_power": 118,
          "max_power": 427,
          "avg_hr": 144,
          "max_hr": 157,
          "avg_cadence": 66.420654,
          "zone": 2,
          "training_load": 8.32866,
          "decoupling": -3.4614036
        },
        {
          "type": "WORK",
          "label": "129s@162w85rpm",
          "duration_secs": 130,
          "avg_power": 160,
          "max_power": 202,
          "avg_hr": 154,
          "max_hr": 156,
          "avg_cadence": 86.26923,
          "zone": 4,
          "training_load": 3.2345698,
          "decoupling": 0.76782024
        },
        {
          "type": "RECOVERY",
          "duration_secs": 515,
          "avg_power": 122,
          "max_power": 318,
          "avg_hr": 145,
          "max_hr": 155,
          "avg_cadence": 75.481926,
          "zone": 2,
          "training_load": 8.34967,
          "decoupling": -9.334315
        },
        {
          "type": "WORK",
          "label": "204s@151w88rpm",
          "duration_secs": 204,
          "avg_power": 153,
          "max_power": 192,
          "avg_hr": 153,
          "max_hr": 160,
          "avg_cadence": 89.29902,
          "zone": 4,
          "training_load": 4.6387,
          "decoupling": 1.6423558
        },
        {
          "type": "RECOVERY",
          "duration_secs": 714,
          "avg_power": 111,
          "max_power": 307,
          "avg_hr": 149,
          "max_hr": 158,
          "avg_cadence": 62.980392,
          "zone": 2,
          "training_load": 11.513227,
          "decoupling": -17.012775
        },
        {
          "type": "WORK",
          "label": "17s@281w90rpm",
          "duration_secs": 17,
          "avg_power": 281,
          "max_power": 339,
          "avg_hr": 147,
          "max_hr": 149,
          "avg_cadence": 90.23529,
          "zone": 7,
          "training_load": 0.27842438,
          "decoupling": 12.310577
        },
        {
          "type": "RECOVERY",
          "duration_secs": 68,
          "avg_power": 103,
          "max_power": 290,
          "avg_hr": 149,
          "max_hr": 155,
          "avg_cadence": 61.10294,
          "zone": 2,
          "training_load": 1.8000126,
          "decoupling": 8.378514
        },
        {
          "type": "WORK",
          "label": "30s@197w84rpm",
          "duration_secs": 25,
          "avg_power": 185,
          "max_power": 264,
          "avg_hr": 148,
          "max_hr": 151,
          "avg_cadence": 76.84,
          "zone": 5,
          "training_load": 0.4031242,
          "decoupling": 14.027511
        },
        {
          "type": "RECOVERY",
          "duration_secs": 382,
          "avg_power": 117,
          "max_power": 271,
          "avg_hr": 149,
          "max_hr": 155,
          "avg_cadence": 70.573296,
          "zone": 2,
          "training_load": 6.25636,
          "decoupling": -10.615099
        }
      ]
    },
    {
      "activity_id": "i158778089",
      "date": "2026-06-20",
      "type": "Run",
      "name": "Bad Lausick - Aerobic Endurance Run",
      "interval_summary": [
        "1x 5m54s 118bpm",
        "6x 6m28s 144bpm",
        "1x 17s 155bpm"
      ],
      "intervals": [
        {
          "type": "WORK",
          "label": "354s@118bpm86rpm",
          "duration_secs": 354,
          "avg_hr": 118,
          "max_hr": 136,
          "avg_cadence": 86.22317,
          "zone": 1
        },
        {
          "type": "WORK",
          "label": "388s@144bpm88rpm",
          "duration_secs": 381,
          "avg_hr": 139,
          "max_hr": 147,
          "avg_cadence": 89.09449,
          "zone": 1
        },
        {
          "type": "WORK",
          "label": "388s@144bpm88rpm",
          "duration_secs": 390,
          "avg_hr": 141,
          "max_hr": 150,
          "avg_cadence": 88.917946,
          "zone": 1
        },
        {
          "type": "WORK",
          "label": "388s@144bpm88rpm",
          "duration_secs": 390,
          "avg_hr": 142,
          "max_hr": 147,
          "avg_cadence": 87.51282,
          "zone": 1
        },
        {
          "type": "WORK",
          "label": "388s@144bpm88rpm",
          "duration_secs": 392,
          "avg_hr": 146,
          "max_hr": 151,
          "avg_cadence": 88.68367,
          "zone": 1
        },
        {
          "type": "WORK",
          "label": "388s@144bpm88rpm",
          "duration_secs": 385,
          "avg_hr": 147,
          "max_hr": 151,
          "avg_cadence": 87.52987,
          "zone": 2
        },
        {
          "type": "WORK",
          "label": "388s@144bpm88rpm",
          "duration_secs": 392,
          "avg_hr": 147,
          "max_hr": 160,
          "avg_cadence": 88.216835,
          "zone": 2
        },
        {
          "type": "WORK",
          "label": "17s@155bpm88rpm",
          "duration_secs": 17,
          "avg_hr": 155,
          "max_hr": 157,
          "avg_cadence": 87.588234,
          "zone": 3
        },
        {
          "type": "RECOVERY",
          "duration_secs": 1,
          "avg_hr": 153,
          "max_hr": 153,
          "avg_cadence": 85.0,
          "zone": 2
        }
      ]
    }
  ]
}